revelsMD/.DS_Store
revelsMD/__init__.py
revelsMD/revels_3D.py
revelsMD/revels_rdf.py
revelsMD/trajectory_states.py
revelsMD/revels_tools/__init__.py
revelsMD/revels_tools/conversion_factors.py
revelsMD/revels_tools/lammps_parser.py
revelsMD/revels_tools/vasp_parser.py
revelsmd-0.1.5.dist-info/WHEEL
revelsmd-0.1.5.dist-info/METADATA
revelsmd-0.1.5.dist-info/RECORD
